{
 "actions": [],
 "allow_rename": 1,
 "creation": "2022-03-08 18:25:13.332094",
 "doctype": "DocType",
 "editable_grid": 1,
 "engine": "InnoDB",
 "field_order": [
  "customer",
  "sku",
  "model",
  "mfg",
  "column_break_4",
  "type",
  "quoted_price",
  "quotation_no",
  "supply_order_data",
  "work_order_data"
 ],
 "fields": [
  {
   "columns": 1,
   "fieldname": "customer",
   "fieldtype": "Link",
   "in_list_view": 1,
   "label": "Customer",
   "options": "Customer"
  },
  {
   "columns": 1,
   "fieldname": "model",
   "fieldtype": "Link",
   "in_list_view": 1,
   "label": "Model",
   "options": "Item Model"
  },
  {
   "columns": 1,
   "fieldname": "mfg",
   "fieldtype": "Link",
   "in_list_view": 1,
   "label": "Mfg",
   "options": "Item Mfg"
  },
  {
   "columns": 1,
   "fieldname": "type",
   "fieldtype": "Link",
   "in_list_view": 1,
   "label": "Type",
   "options": "Item Type"
  },
  {
   "columns": 1,
   "fieldname": "quoted_price",
   "fieldtype": "Currency",
   "in_list_view": 1,
   "label": "Quoted Price"
  },
  {
   "columns": 2,
   "fieldname": "quotation_no",
   "fieldtype": "Link",
   "in_list_view": 1,
   "label": "Quotation No",
   "options": "Quotation"
  },
  {
   "fieldname": "column_break_4",
   "fieldtype": "Column Break"
  },
  {
   "columns": 1,
   "fieldname": "sku",
   "fieldtype": "Link",
   "in_list_view": 1,
   "label": "SKU",
   "options": "Item"
  },
  {
   "columns": 1,
   "fieldname": "supply_order_data",
   "fieldtype": "Link",
   "in_list_view": 1,
   "label": "Supply Order Data",
   "options": "Supply Order Data"
  },
  {
   "columns": 1,
   "fieldname": "work_order_data",
   "fieldtype": "Link",
   "in_list_view": 1,
   "label": "Work Order Data",
   "options": "Work Order Data"
  }
 ],
 "index_web_pages_for_search": 1,
 "istable": 1,
 "links": [],
 "modified": "2023-01-05 08:43:27.081020",
 "modified_by": "Administrator",
 "module": "Tsl",
 "name": "Similar Item Repair",
 "owner": "Administrator",
 "permissions": [],
 "sort_field": "modified",
 "sort_order": "DESC"
}